sneak/__init__.py
sneak/cli.py
sneak/config.py
sneak/game.py
sneak/run.py
sneak/stage.py
sneak/terminal.py
sneak/theme.py
sneak_game-0.2.0.data/scripts/sneak
sneak_game-0.2.0.dist-info/LICENSE
sneak_game-0.2.0.dist-info/METADATA
sneak_game-0.2.0.dist-info/WHEEL
sneak_game-0.2.0.dist-info/top_level.txt
sneak_game-0.2.0.dist-info/RECORD
