Metadata-Version: 2.1
Name: sneak-game
Version: 0.2.0
Summary: Terminal snake in Python
Home-page: https://github.com/bluecap-se/sneak
Author: bluecap-se
Author-email: hello@bluecap.se
License: MIT
Keywords: sneak,game,snake
Platform: any
Classifier: Development Status :: 5 - Production/Stable
Classifier: Environment :: Console
Classifier: Intended Audience :: Developers
Classifier: Intended Audience :: End Users/Desktop
Classifier: License :: OSI Approved :: MIT License
Classifier: Natural Language :: English
Classifier: Operating System :: MacOS
Classifier: Operating System :: POSIX
Classifier: Programming Language :: Python :: 3 :: Only
Classifier: Topic :: Games/Entertainment :: Arcade
License-File: LICENSE
Requires-Dist: docopt (==0.6.2)
